mpfa/__init__.py
mpfa/__main__.py
mpfa/core/__init__.py
mpfa/tests/__init__.py
mpfa/tests/test_1984.py
mpfa-0.0.0.dev0.dist-info/LICENSE.txt
mpfa-0.0.0.dev0.dist-info/METADATA
mpfa-0.0.0.dev0.dist-info/WHEEL
mpfa-0.0.0.dev0.dist-info/top_level.txt
mpfa-0.0.0.dev0.dist-info/RECORD
