Metadata-Version: 2.2
Name: mpfa
Version: 0.0.0.dev0
Summary: mpfa
Author-email: Johannes <johannes-programming@mailfence.com>
License: The MIT License (MIT)
Project-URL: Download, https://pypi.org/project/mpfa/#files
Project-URL: Index, https://pypi.org/project/mpfa/
Project-URL: Source, https://github.com/johannes-programming/mpfa/
Classifier: Development Status :: 1 - Planning
Classifier: License :: OSI Approved :: MIT License
Classifier: Natural Language :: English
Classifier: Operating System :: OS Independent
Classifier: Programming Language :: Python
Classifier: Programming Language :: Python :: 3
Classifier: Programming Language :: Python :: 3 :: Only
Classifier: Typing :: Typed
Requires-Python: >=3.12.7
License-File: LICENSE.txt
